[ {
  "id" : 3,
  "purchasedCart" : {
    "id" : 3,
    "contents" : [ {
      "id" : 4,
      "name" : "Squirtle",
      "types" : [ "WATER" ],
      "quantity" : 10,
      "price" : 3.99
    }, {
      "id" : 6,
      "name" : "Mudkip",
      "types" : [ "WATER" ],
      "quantity" : 30,
      "price" : 3.99
    }, {
      "id" : 11,
      "name" : "Volcarona",
      "types" : [ "FIRE", "GRASS" ],
      "quantity" : 1,
      "price" : 2500.0
    }, {
      "id" : 5,
      "name" : "Treecko",
      "types" : [ "GRASS" ],
      "quantity" : 5,
      "price" : 2.99
    } ],
    "totalPrice" : 2674.55
  },
  "orderNumber" : 1,
  "timeStamp" : "11/13/2022 13:10:19"
}, {
  "id" : 3,
  "purchasedCart" : {
    "id" : 3,
    "contents" : [ {
      "id" : 2,
      "name" : "Bulbasaur",
      "types" : [ "GRASS" ],
      "quantity" : 1,
      "price" : 2.0
    }, {
      "id" : 3,
      "name" : "Charmander",
      "types" : [ "FIRE" ],
      "quantity" : 2,
      "price" : 4.5
    }, {
      "id" : 1,
      "name" : "Pikachu",
      "types" : [ "ELECTRIC" ],
      "quantity" : 1,
      "price" : 9.0
    }, {
      "id" : 4,
      "name" : "Squirtle",
      "types" : [ "WATER" ],
      "quantity" : 2,
      "price" : 3.99
    } ],
    "totalPrice" : 27.98
  },
  "orderNumber" : 2,
  "timeStamp" : "11/13/2022 13:11:04"
}, {
  "id" : 2,
  "purchasedCart" : {
    "id" : 2,
    "contents" : [ {
      "id" : 12,
      "name" : "Emboar",
      "types" : [ "FIRE", "FIGHTING" ],
      "quantity" : 1,
      "price" : 1.0
    }, {
      "id" : 10,
      "name" : "Blastoise",
      "types" : [ "WATER" ],
      "quantity" : 3,
      "price" : 20.48
    }, {
      "id" : 7,
      "name" : "Torchic",
      "types" : [ "FIRE" ],
      "quantity" : 5,
      "price" : 2.0
    } ],
    "totalPrice" : 72.44
  },
  "orderNumber" : 3,
  "timeStamp" : "11/13/2022 13:11:39"
} ]